mccnado/__init__.py
mccnado/cli.py
mccnado/mccnado.cpython-312-darwin.so
mccnado/storage.py
mccnado-0.1.5.dist-info/METADATA
mccnado-0.1.5.dist-info/WHEEL
mccnado-0.1.5.dist-info/entry_points.txt
mccnado-0.1.5.dist-info/RECORD
