Metadata-Version: 2.4
Name: mccnado
Version: 0.1.5
Classifier: Programming Language :: Rust
Classifier: Programming Language :: Python :: Implementation :: CPython
Classifier: Programming Language :: Python :: Implementation :: PyPy
Requires-Dist: typer
Requires-Dist: loguru
Requires-Dist: cooler
Requires-Dist: h5py
Requires-Dist: pysam
Requires-Dist: pytest ; extra == 'tests'
Requires-Dist: pysam ; extra == 'tests'
Provides-Extra: tests
Summary: MCCNado: Rust-based tools for use in processing Micro-Capure-C data using SeqNado
Author-email: Alastair Smith <alastair.smith@ndcls.ox.ac.uk>
Maintainer-email: Alastair Smith <alastair.smith@ndcls.ox.ac.uk>
License: GPL-3.0-or-later
Requires-Python: >=3.10
